{
  "currentTerm": 0,
  "log": {
    "R5FTH": [
      {
        "strokeId": "447a9a81-92f6-4473-8708-edf8ce4fee6a",
        "roomId": "R5FTH",
        "userName": "myth",
        "startX": 134,
        "startY": 222,
        "endX": 137,
        "endY": 232,
        "color": "#000000",
        "thickness": 5,
        "tool": "pen"
      },
      {
        "strokeId": "447a9a81-92f6-4473-8708-edf8ce4fee6a",
        "roomId": "R5FTH",
        "userName": "myth",
        "startX": 137,
        "startY": 232,
        "endX": 154,
        "endY": 268,
        "color": "#000000",
        "thickness": 5,
        "tool": "pen"
      },
      {
        "strokeId": "73ad703f-a0e1-462f-8daf-420d76debd83",
        "roomId": "R5FTH",
        "userName": "myth",
        "startX": 424,
        "startY": 301,
        "endX": 406,
        "endY": 337,
        "color": "#000000",
        "thickness": 5,
        "tool": "pen"
      }
    ]
  }
}